kjetilko_dagens_lunch/__init__.py
kjetilko_dagens_lunch/cli.py
kjetilko_dagens_lunch-0.1.3.dist-info/LICENSE
kjetilko_dagens_lunch-0.1.3.dist-info/METADATA
kjetilko_dagens_lunch-0.1.3.dist-info/WHEEL
kjetilko_dagens_lunch-0.1.3.dist-info/entry_points.txt
kjetilko_dagens_lunch-0.1.3.dist-info/RECORD
