Metadata-Version: 2.3
Name: kjetilko_dagens_lunch
Version: 0.1.3
Summary: Get and display Dagens Lunch from TU.no
Author: redacted Datascience
Author-email: Datascience.Drift@redacted.no
Requires-Python: >=3.7,<4.0
Classifier: Programming Language :: Python :: 3
Classifier: Programming Language :: Python :: 3.7
Classifier: Programming Language :: Python :: 3.8
Classifier: Programming Language :: Python :: 3.9
Classifier: Programming Language :: Python :: 3.10
Classifier: Programming Language :: Python :: 3.11
Classifier: Programming Language :: Python :: 3.12
Classifier: Programming Language :: Python :: 3.13
Requires-Dist: bs4 (>=0.0.1,<0.0.2)
Requires-Dist: pillow (>=8.0.1,<9.0.0)
Requires-Dist: requests (>=2.25.0,<3.0.0)
Requires-Dist: typer (>=0.3.2,<0.4.0)
Project-URL: Repository, https://gitlab.redacted.no/kjetilko/kjetilko-dagens-lunch.git
